<?xml version = "1.0" encoding = "utf-8" ?>
<problem
	version = "1.0"
	id = "ru.olymp.spb.2021.day2.a-plus-b"
>
	<judging>
		<script type = "%icpc">
			<testset
				input-name = "*"
				output-name = "*"
				input-href = "tests/##"
				answer-href = "tests/##.a"
				time-limit = "1.0s"
				memory-limit = "536870912"
				test-count = "128"
			>
			</testset>
			<verifier type = "%testlib">
				<binary executable-id = "x86.exe.win32" file = "check.exe" />
			</verifier>
		</script>
		<script type = "%ioi">
			<testset
				name = "preliminary"
				input-name = "*"
				output-name = "*"
				input-href = "tests/##"
				answer-href = "tests/##.a"
				time-limit = "1.0s"
				memory-limit = "536870912"
			>
				<test comment = "manual cmd: ''" />
				<test comment = "manual cmd: ''" />
				<test comment = "manual cmd: ''" />
				<test comment = "manual cmd: ''" />
			</testset>
			<testset
				name = "main"
				input-name = "*"
				output-name = "*"
				input-href = "tests/##"
				answer-href = "tests/##.a"
				time-limit = "1.0s"
				memory-limit = "536870912"
			>
				<test-group
					comment = "Sample tests"
					scoring = "sum"
					feedback = "statistics"
					group-bonus = "0"
					require-groups = ""
				>
					<test comment = "manual cmd: ''" />
					<test comment = "manual cmd: ''" />
					<test comment = "manual cmd: ''" />
					<test comment = "manual cmd: ''" />
				</test-group>
				<test-group
					comment = "1"
					scoring = "group"
					feedback = "group-score-and-test"
					group-bonus = "7"
					require-groups = "1 "
				>
					<test comment = "generated cmd: 'gen 2 0 0 0'" />
					<test comment = "generated cmd: 'gen 0 1 1 0'" />
					<test comment = "generated cmd: 'gen 0 1 1 0 noZero'" />
					<test comment = "generated cmd: 'gen 0 1 1 1'" />
					<test comment = "generated cmd: 'gen 1 1 1 0'" />
					<test comment = "generated cmd: 'gen 6 0 0 0'" />
					<test comment = "generated cmd: 'gen 0 3 3 0'" />
					<test comment = "generated cmd: 'gen 0 3 3 0 noZero'" />
					<test comment = "generated cmd: 'gen 0 0 0 6'" />
					<test comment = "generated cmd: 'gen 2 2 2 0'" />
					<test comment = "generated cmd: 'gen 0 2 2 2'" />
					<test comment = "generated cmd: 'gen 2 0 0 4'" />
					<test comment = "generated cmd: 'gen 2 1 1 2'" />
					<test comment = "generated cmd: 'gen 4 1 1 0'" />
					<test comment = "generated cmd: 'gen 2 1 1 2 allZero'" />
					<test comment = "generated cmd: 'gen 2 1 1 2 badDigit noZero'" />
					<test comment = "generated cmd: 'gen 2 1 1 2 badDigit'" />
				</test-group>
				<test-group
					comment = "2"
					scoring = "group"
					feedback = "group-score-and-test"
					group-bonus = "14"
					require-groups = "1 2 "
				>
					<test comment = "generated cmd: 'gen 4 5 5 4 noZero'" />
					<test comment = "generated cmd: 'gen 6 5 5 2 noZero'" />
					<test comment = "generated cmd: 'gen 7 2 2 7 noZero'" />
					<test comment = "generated cmd: 'gen 6 2 2 8 noZero'" />
					<test comment = "generated cmd: 'gen 7 1 1 9 noZero'" />
					<test comment = "generated cmd: 'gen 4 5 5 4'" />
					<test comment = "generated cmd: 'gen 6 5 5 2'" />
					<test comment = "generated cmd: 'gen 7 2 2 7'" />
					<test comment = "generated cmd: 'gen 6 2 2 8'" />
					<test comment = "generated cmd: 'gen 7 1 1 9'" />
					<test comment = "generated cmd: 'gen 13 2 2 1'" />
					<test comment = "generated cmd: 'gen 2 1 1 14'" />
					<test comment = "generated cmd: 'gen 0 9 9 0'" />
					<test comment = "generated cmd: 'gen 10 0 0 8'" />
					<test comment = "generated cmd: 'gen 0 0 0 18'" />
					<test comment = "generated cmd: 'gen 18 0 0 0'" />
					<test comment = "generated cmd: 'gen 3 5 6 4'" />
					<test comment = "generated cmd: 'gen 5 5 3 5'" />
					<test comment = "generated cmd: 'gen 6 5 5 2 badDigit'" />
					<test comment = "generated cmd: 'gen 7 2 2 7 allZero'" />
				</test-group>
				<test-group
					comment = "3"
					scoring = "group"
					feedback = "group-score-and-test"
					group-bonus = "15"
					require-groups = ""
				>
					<test comment = "generated cmd: 'gen 50 50 50 50 noZero'" />
					<test comment = "generated cmd: 'gen 54 47 47 51 noZero'" />
					<test comment = "generated cmd: 'gen 66 33 33 66 noZero'" />
					<test comment = "generated cmd: 'gen 64 35 35 63 noZero'" />
					<test comment = "generated cmd: 'gen 95 2 2 101 noZero'" />
					<test comment = "generated cmd: 'gen 190 3 3 2 noZero'" />
					<test comment = "generated cmd: 'gen 4 2 2 189 noZero'" />
					<test comment = "generated cmd: 'gen 0 98 98 0 noZero'" />
					<test comment = "generated cmd: 'gen 101 0 0 99 noZero'" />
					<test comment = "generated cmd: 'gen 0 0 0 200 noZero'" />
					<test comment = "generated cmd: 'gen 197 0 0 0 noZero'" />
					<test comment = "generated cmd: 'gen 47 49 48 52 noZero'" />
					<test comment = "generated cmd: 'gen 66 33 35 62 noZero'" />
					<test comment = "generated cmd: 'gen 51 48 48 52 badDigit noZero'" />
				</test-group>
				<test-group
					comment = "4"
					scoring = "group"
					feedback = "group-score-and-test"
					group-bonus = "5"
					require-groups = "1 2 3 4 "
				>
					<test comment = "generated cmd: 'gen 50 50 50 50'" />
					<test comment = "generated cmd: 'gen 54 47 47 51'" />
					<test comment = "generated cmd: 'gen 66 33 33 66'" />
					<test comment = "generated cmd: 'gen 64 35 35 63'" />
					<test comment = "generated cmd: 'gen 95 2 2 101'" />
					<test comment = "generated cmd: 'gen 190 3 3 2'" />
					<test comment = "generated cmd: 'gen 4 2 2 189'" />
					<test comment = "generated cmd: 'gen 0 98 98 0'" />
					<test comment = "generated cmd: 'gen 101 0 0 99'" />
					<test comment = "generated cmd: 'gen 0 0 0 200'" />
					<test comment = "generated cmd: 'gen 197 0 0 0'" />
					<test comment = "generated cmd: 'gen 47 49 48 52'" />
					<test comment = "generated cmd: 'gen 66 33 35 62'" />
					<test comment = "generated cmd: 'gen 51 48 48 52 badDigit'" />
					<test comment = "generated cmd: 'gen 45 50 50 55 allZero'" />
				</test-group>
				<test-group
					comment = "5"
					scoring = "group"
					feedback = "group-score-and-test"
					group-bonus = "17"
					require-groups = "4 "
				>
					<test comment = "generated cmd: 'gen 188 187 187 188 noZero'" />
					<test comment = "generated cmd: 'gen 180 185 185 193 noZero'" />
					<test comment = "generated cmd: 'gen 250 125 125 250 noZero'" />
					<test comment = "generated cmd: 'gen 258 121 121 245 noZero'" />
					<test comment = "generated cmd: 'gen 370 2 2 376 noZero'" />
					<test comment = "generated cmd: 'gen 742 2 2 1 noZero'" />
					<test comment = "generated cmd: 'gen 3 2 2 740 noZero'" />
					<test comment = "generated cmd: 'gen 0 374 374 0 noZero'" />
					<test comment = "generated cmd: 'gen 379 0 0 369 noZero'" />
					<test comment = "generated cmd: 'gen 0 0 0 750 noZero'" />
					<test comment = "generated cmd: 'gen 748 0 0 0 noZero'" />
					<test comment = "generated cmd: 'gen 180 185 184 193 noZero'" />
					<test comment = "generated cmd: 'gen 250 125 127 245 noZero'" />
					<test comment = "generated cmd: 'gen 250 123 123 251 badDigit noZero'" />
				</test-group>
				<test-group
					comment = "6"
					scoring = "group"
					feedback = "group-score-and-test"
					group-bonus = "5"
					require-groups = "1 2 3 4 5 6 "
				>
					<test comment = "generated cmd: 'gen 188 187 187 188'" />
					<test comment = "generated cmd: 'gen 180 185 185 193'" />
					<test comment = "generated cmd: 'gen 250 125 125 250'" />
					<test comment = "generated cmd: 'gen 258 121 121 245'" />
					<test comment = "generated cmd: 'gen 370 2 2 376'" />
					<test comment = "generated cmd: 'gen 742 2 2 1'" />
					<test comment = "generated cmd: 'gen 3 2 2 740'" />
					<test comment = "generated cmd: 'gen 0 374 374 0'" />
					<test comment = "generated cmd: 'gen 379 0 0 369'" />
					<test comment = "generated cmd: 'gen 0 0 0 750'" />
					<test comment = "generated cmd: 'gen 748 0 0 0'" />
					<test comment = "generated cmd: 'gen 180 185 184 193'" />
					<test comment = "generated cmd: 'gen 250 125 127 245'" />
					<test comment = "generated cmd: 'gen 250 123 123 251 badDigit'" />
					<test comment = "generated cmd: 'gen 248 126 126 245 allZero'" />
				</test-group>
				<test-group
					comment = "7"
					scoring = "group"
					feedback = "group-score-and-test"
					group-bonus = "20"
					require-groups = "4 6 "
				>
					<test comment = "generated cmd: 'gen 50000 50000 50000 50000 noZero'" />
					<test comment = "generated cmd: 'gen 50123 50322 50322 49011 noZero'" />
					<test comment = "generated cmd: 'gen 66666 33333 33333 66666 noZero'" />
					<test comment = "generated cmd: 'gen 66611 34001 34001 64111 noZero'" />
					<test comment = "generated cmd: 'gen 99990 9 9 99975 noZero'" />
					<test comment = "generated cmd: 'gen 199981 6 6 5 noZero'" />
					<test comment = "generated cmd: 'gen 8 7 7 199958 noZero'" />
					<test comment = "generated cmd: 'gen 0 99998 99998 0 noZero'" />
					<test comment = "generated cmd: 'gen 100001 0 0 99876 noZero'" />
					<test comment = "generated cmd: 'gen 0 0 0 200000 noZero'" />
					<test comment = "generated cmd: 'gen 199998 0 0 0 noZero'" />
					<test comment = "generated cmd: 'gen 50123 50322 50321 49011 noZero'" />
					<test comment = "generated cmd: 'gen 66662 33333 33335 66666 noZero'" />
					<test comment = "generated cmd: 'gen 51001 50001 50001 48022 badDigit noZero'" />
				</test-group>
				<test-group
					comment = "8"
					scoring = "group"
					feedback = "group-score-and-test"
					group-bonus = "17"
					require-groups = "1 2 3 4 5 6 7 8 "
				>
					<test comment = "generated cmd: 'gen 50000 50000 50000 50000'" />
					<test comment = "generated cmd: 'gen 50123 50322 50322 49011'" />
					<test comment = "generated cmd: 'gen 66666 33333 33333 66666'" />
					<test comment = "generated cmd: 'gen 66611 34001 34001 64111'" />
					<test comment = "generated cmd: 'gen 99990 9 9 99975'" />
					<test comment = "generated cmd: 'gen 199981 6 6 5'" />
					<test comment = "generated cmd: 'gen 8 7 7 199958'" />
					<test comment = "generated cmd: 'gen 0 99998 99998 0'" />
					<test comment = "generated cmd: 'gen 100001 0 0 99876'" />
					<test comment = "generated cmd: 'gen 0 0 0 200000'" />
					<test comment = "generated cmd: 'gen 199998 0 0 0'" />
					<test comment = "generated cmd: 'gen 50123 50322 50321 49011'" />
					<test comment = "generated cmd: 'gen 66662 33333 33335 66666'" />
					<test comment = "generated cmd: 'gen 51001 50001 50001 48022 badDigit'" />
					<test comment = "generated cmd: 'gen 51001 50000 50000 48022 allZero'" />
				</test-group>
			</testset>
			<verifier type = "%testlib">
				<binary executable-id = "x86.exe.win32" file = "check.exe" />
			</verifier>
		</script>
	</judging>
</problem>
